queuepool/__init__.py
queuepool/pool.py
queuepool/psycopg2cm.py
queuepool/psycopg2cm_tests.py
queuepool/smtpcm.py
queuepool-1.3.2.dist-info/AUTHORS
queuepool-1.3.2.dist-info/LICENSE
queuepool-1.3.2.dist-info/METADATA
queuepool-1.3.2.dist-info/WHEEL
queuepool-1.3.2.dist-info/top_level.txt
queuepool-1.3.2.dist-info/RECORD
