Metadata-Version: 2.1
Name: queuepool
Version: 1.3.2
Summary: A multithread-safe resource pool based on synchronized queue
Home-page: https://github.com/ikhomyakov/queuepool
Author: ikh software, inc.
Author-email: ikh@ikhsoftware.com
License: UNKNOWN
Project-URL: Bug Reports, https://github.com/ikhomyakov/queuepool/issues
Platform: UNKNOWN
Classifier: Programming Language :: Python :: 3
Classifier: License :: OSI Approved :: BSD License
Classifier: Operating System :: OS Independent
Requires-Python: >= 3.7
Requires-Dist: psycopg2 (>=2.8.2)
